GaonSidedrawer/__init__.py
GaonSidedrawer/main.py
GaonSidedrawer/utils.py
tests/__init__.py
tests/test_main.py
Gaon-0.2.dist-info/LICENSE
Gaon-0.2.dist-info/METADATA
Gaon-0.2.dist-info/WHEEL
Gaon-0.2.dist-info/top_level.txt
Gaon-0.2.dist-info/RECORD
