Metadata-Version: 2.1
Name: Gaon
Version: 0.2
Summary: AI library for Sidedrawer
Author: Gaon.ai
Author-email: support@gaon.ai
License: MIT
License-File: LICENSE
Requires-Dist: pdf2image
Requires-Dist: opencv-python
Requires-Dist: pytesseract
Requires-Dist: numpy
Requires-Dist: pandas
Requires-Dist: scikit-learn
